{"site":{"title":"Stratup template","description":null,"enableMobile":true,"websiteUrl":null,"faviconPath":null,"thumbnailSocialPath":null,"descriptionSocial":null,"titleSocial":null,"lang":"","width":1011,"headUser":"<link rel=\"stylesheet\" href=\"fancybox/source/jquery.fancybox.css?v=2.1.5\" type=\"text/css\" media=\"screen\" />\n<script type=\"text/javascript\" src=\"fancybox/source/jquery.fancybox.pack.js?v=2.1.5\"></script>\n","headStyle":"div.hero {\n  min-height: 95vh;\n}\n\n.text-shadow {\n    text-shadow: 0 0 1.5px black;\n}\n\n.fancybox {\n    cursor: pointer;\n}\n.myButton {\n\tbox-shadow:inset 0px 1px 0px 0px #ffffff;\n\tbackground:linear-gradient(to bottom, #ffffff 5%, #f6f6f6 100%);\n\tbackground-color:#ffffff;\n\tborder-radius:6px;\n\tborder:1px solid #dcdcdc;\n\tdisplay:inline-block;\n\tcursor:pointer;\n\tcolor:#666666;\n\tfont-family:Arial;\n\tfont-size:15px;\n\tfont-weight:bold;\n\tpadding:6px 24px;\n\ttext-decoration:none;\n\ttext-shadow:0px 1px 0px #ffffff;\n}\n.myButton:hover {\n\tbackground:linear-gradient(to bottom, #f6f6f6 5%, #ffffff 100%);\n\tbackground-color:#f6f6f6;\n}\n.myButton:active {\n\tposition:relative;\n\ttop:1px;\n}\n","headScript":"        $(document).ready(function() {\n        \t$('.fancybox').each(function () {\n        \t    var href = this.getAttribute('data-silex-href') || this.getAttribute('href');\n        \t    if (this.getAttribute('data-silex-href')) {\n            \t    this.removeAttribute('data-silex-href');\n            \t    // for the fancybox script\n            \t    this.setAttribute('href', href);\n            \t    // prevent silex from opening link\n            \t    $(this).off('click');\n        \t    }\n        \t    // this is a galery\n        \t    this.setAttribute('data-fancybox-group', 'group1');\n        \t});\n        \t// create the fancybox\n        \t$('.fancybox').fancybox();\n        });\n    ","hostingProvider":"unifile","twitterSocial":null,"dataSources":{},"fonts":[{"family":"'Roboto', sans-serif","href":"https://fonts.googleapis.com/css?family=Roboto"},{"family":"'Noto Sans JP', light","href":"https://fonts.googleapis.com/css2?family=Noto+Sans+JP"}],"styles":{"all-style":{"className":"all-style","templateName":"text","displayName":"All style","styles":{"desktop":{"normal":{"className":"all-style","pseudoClass":"normal","All":{"font-family":"'Noto Sans JP', light","color":"#000000","font-size":"16px","text-align":"left","line-height":"1.5","border":{"border-style":""},"transition":[],"padding":{"padding-top":""},"margin":{"margin-top":""},"background-color":""},"Heading1":{"color":"#DDDDDD","font-weight":"normal","text-align":"center"},"Heading2":{"font-weight":"normal","font-size":"","color":"#999999","text-align":"left","line-height":""},"Link":{"text-decoration":"none","color":"#ce8547"},"Bold":{"font-size":"32px","color":"#292929","background-color":""}},":hover":{"templateName":"text","className":"all-style","pseudoClass":":hover","All":{"transition":[],"background-color":"","font-size":""}}},"mobile":{"normal":{"templateName":"text","className":"all-style","pseudoClass":"normal","All":{"font-size":"160%","color":"#666666"},"Heading2":{"text-align":"center","line-height":""},"Heading1":{"color":"#666666"}}}}},"centered-text":{"className":"centered-text","templateName":"text","displayName":"Centered text","styles":{"desktop":{"normal":{"templateName":"text","className":"centered-text","pseudoClass":"normal","All":{"text-align":"center","color":"#ffffff","line-height":"2","font-size":"32px","border":{"border-style":""},"letter-spacing":""},"Heading1":{"font-family":"'Roboto', sans-serif"},"Bold":{"color":"#ffffff","line-height":"","font-size":"36px"}}}}},"style-button-text-box":{"className":"style-button-text-box","templateName":"text","displayName":"Button text box","styles":{"desktop":{"normal":{"templateName":"text","className":"style-button-text-box","pseudoClass":"normal","All":{"text-align":"center"}}}}}},"isTemplate":false,"file":{"name":"cc.html","folder":"portfolio_presentation/main/CC","path":"portfolio_presentation/main/CC/cc.html","service":"github","url":"https://editor.silex.me/ce/github/get/portfolio_presentation/main/CC/cc.html","absPath":"/ce/github/get/portfolio_presentation/main/CC/cc.html"},"prodotypeDependencies":{},"data":{}},"pages":[{"id":"page-home","displayName":"Home","link":{"linkType":"LinkTypePage","href":"#!page-home"},"canDelete":true,"canProperties":true,"canMove":true,"canRename":true,"opened":false}],"elements":[{"id":"body-initial","pageNames":[],"classList":[],"type":"container-element","isSectionContent":false,"title":"","alt":null,"children":["silex-id-1617857338966-32","silex-id-1617858193488-41","silex-id-1617860681193-50","silex-id-1617860677610-48","silex-id-1617899053148-3","silex-id-1617899266343-6","silex-id-1617900427272-0","silex-id-1618027742671-0","silex-id-1618027759003-3"],"link":null,"enableEdit":false,"enableDrag":false,"enableDrop":true,"enableResize":{"top":false,"bottom":false,"left":false,"right":false},"selected":false,"useMinHeight":true,"visibility":{"desktop":true,"mobile":true},"style":{"desktop":{"position":"static","background-color":"rgba(255,255,255,1)"},"mobile":{}},"data":{"component":null},"innerHtml":"","tagName":"BODY"},{"id":"silex-id-1617857338966-32","tagName":"DIV","type":"text-element","alt":null,"title":null,"isSectionContent":false,"visibility":{"desktop":true,"mobile":true},"style":{"mobile":{},"desktop":{"width":"639px","height":"56px","position":"absolute","top":"1278px","left":"777px"}},"data":{"component":null},"children":[],"pageNames":["page-home"],"classList":[],"link":null,"enableEdit":true,"enableDrag":true,"enableDrop":false,"enableResize":{"top":true,"bottom":true,"left":true,"right":true},"selected":false,"useMinHeight":true,"innerHtml":"\n<h3><b>Natural Sims: Mountain range<br></b></h3>"},{"id":"silex-id-1617858193488-41","tagName":"DIV","type":"text-element","alt":null,"title":null,"isSectionContent":false,"visibility":{"desktop":true,"mobile":true},"style":{"mobile":{},"desktop":{"width":"639px","height":"56px","position":"absolute","top":"1541px","left":"777px"}},"data":{"component":null},"children":[],"pageNames":["page-home"],"classList":[],"link":null,"enableEdit":true,"enableDrag":true,"enableDrop":false,"enableResize":{"top":true,"bottom":true,"left":true,"right":true},"selected":false,"useMinHeight":true,"innerHtml":"\n<h3><b>AP: Programming<br></b></h3>"},{"id":"silex-id-1617860677610-48","tagName":"DIV","type":"html-element","alt":null,"title":null,"isSectionContent":false,"visibility":{"desktop":true,"mobile":true},"style":{"mobile":{},"desktop":{"width":"62px","height":"32px","background-color":"transparent","position":"absolute","top":"1333.7999267578125px","left":"777px"}},"data":{"component":null},"children":[],"pageNames":["page-home"],"classList":[],"link":null,"enableEdit":true,"enableDrag":true,"enableDrop":false,"enableResize":{"top":true,"bottom":true,"left":true,"right":true},"selected":false,"useMinHeight":true,"innerHtml":"<a href=\"mount/mount.html\" class=\"myButton\">View</a>"},{"id":"silex-id-1617860681193-50","tagName":"DIV","type":"html-element","alt":null,"title":null,"isSectionContent":false,"visibility":{"desktop":true,"mobile":true},"style":{"mobile":{},"desktop":{"width":"62px","height":"32px","background-color":"transparent","position":"absolute","top":"1597.2498168945312px","left":"777px"}},"data":{"component":null},"children":[],"pageNames":["page-home"],"classList":[],"link":null,"enableEdit":true,"enableDrag":true,"enableDrop":false,"enableResize":{"top":true,"bottom":true,"left":true,"right":true},"selected":false,"useMinHeight":true,"innerHtml":"<a href=\"bookshelf/Bookshelf.html\" class=\"myButton\">View</a>"},{"id":"silex-id-1617899053148-3","tagName":"SECTION","type":"section-element","alt":null,"title":null,"isSectionContent":false,"visibility":{"desktop":true,"mobile":true},"style":{"mobile":{},"desktop":{"position":"static","background-color":"transparent"}},"data":{"component":null},"children":["silex-id-1617899053148-4"],"pageNames":["page-home"],"classList":[],"link":null,"enableEdit":false,"enableDrag":true,"enableDrop":true,"enableResize":{"top":false,"bottom":false,"left":false,"right":false},"selected":false,"useMinHeight":true,"innerHtml":""},{"id":"silex-id-1617899053148-4","tagName":"DIV","type":"container-element","alt":null,"title":null,"isSectionContent":true,"visibility":{"desktop":true,"mobile":true},"style":{"desktop":{"height":"20px","background-color":"rgba(255,255,255,1)","position":"relative","margin-left":"auto","margin-right":"auto","padding-top":"100px"},"mobile":{}},"data":{"component":null},"children":["silex-id-1617899894619-11"],"pageNames":[],"classList":["silex-element-content","website-width","prevent-draggable"],"link":null,"enableEdit":false,"enableDrag":false,"enableDrop":true,"enableResize":{"top":true,"bottom":true,"left":true,"right":true},"selected":false,"useMinHeight":true,"innerHtml":""},{"id":"silex-id-1617899266343-6","tagName":"SECTION","type":"section-element","alt":null,"title":null,"isSectionContent":false,"visibility":{"desktop":true,"mobile":true},"style":{"mobile":{},"desktop":{"position":"static","background-color":"transparent"}},"data":{"component":null},"children":["silex-id-1617899266344-7"],"pageNames":["page-home"],"classList":[],"link":null,"enableEdit":false,"enableDrag":true,"enableDrop":true,"enableResize":{"top":false,"bottom":false,"left":false,"right":false},"selected":false,"useMinHeight":true,"innerHtml":""},{"id":"silex-id-1617899266344-7","tagName":"DIV","type":"container-element","alt":null,"title":null,"isSectionContent":true,"visibility":{"desktop":true,"mobile":true},"style":{"desktop":{"height":"479px","background-color":"rgb(255, 255, 255)","position":"relative","margin-left":"auto","margin-right":"auto","display":"flex","align-items":"center","justify-content":"stretch"},"mobile":{}},"data":{"component":null},"children":["silex-id-1617900473664-2"],"pageNames":[],"classList":["silex-element-content","website-width","prevent-draggable"],"link":null,"enableEdit":false,"enableDrag":false,"enableDrop":true,"enableResize":{"top":true,"bottom":true,"left":true,"right":true},"selected":false,"useMinHeight":true,"innerHtml":""},{"id":"silex-id-1617899269927-8","tagName":"DIV","type":"text-element","alt":null,"title":null,"isSectionContent":false,"visibility":{"desktop":true,"mobile":true},"style":{"mobile":{},"desktop":{"width":"973px","height":"192px","position":"absolute","top":"14px","left":"-1px"}},"data":{"component":null},"children":[],"pageNames":[],"classList":[],"link":null,"enableEdit":true,"enableDrag":true,"enableDrop":false,"enableResize":{"top":true,"bottom":true,"left":true,"right":true},"selected":false,"useMinHeight":true,"innerHtml":"\n          <b>The Coding Challenge</b> is a challenge created by The Coding Train. Daniel Shiffman codes a different project every time, in either p5.js, or Processing. One of out projects this year was choosing a coding challenge,&nbsp; completing it, and\n          then teaching our class about it. <br><br> I learned a lot from this challenge.I had trouble understanding how the particles work, so there was a lot of tinkering happening. I refactored the original project, into a liquid-like simulation.\n          Although it still follows the flocking rules. I learned about forces, particles, collisions, and gravity.\n\n        "},{"id":"silex-id-1617899894619-11","tagName":"H1","type":"text-element","alt":null,"title":null,"isSectionContent":false,"visibility":{"desktop":true,"mobile":true},"style":{"mobile":{},"desktop":{"width":"685px","height":"60px","position":"absolute","top":"37px","left":"-1px"}},"data":{"component":null},"children":[],"pageNames":[],"classList":[],"link":null,"enableEdit":true,"enableDrag":true,"enableDrop":false,"enableResize":{"top":true,"bottom":true,"left":true,"right":true},"selected":false,"useMinHeight":true,"innerHtml":"<b>Flocking simulation<br></b>"},{"id":"silex-id-1617900427272-0","tagName":"SECTION","type":"section-element","alt":null,"title":null,"isSectionContent":false,"visibility":{"desktop":true,"mobile":true},"style":{"mobile":{},"desktop":{"position":"static","background-color":"transparent"}},"data":{"component":null},"children":["silex-id-1617900427273-1"],"pageNames":["page-home"],"classList":[],"link":null,"enableEdit":false,"enableDrag":true,"enableDrop":true,"enableResize":{"top":false,"bottom":false,"left":false,"right":false},"selected":false,"useMinHeight":true,"innerHtml":""},{"id":"silex-id-1617900427273-1","tagName":"DIV","type":"container-element","alt":null,"title":null,"isSectionContent":true,"visibility":{"desktop":true,"mobile":true},"style":{"desktop":{"height":"226px","background-color":"rgb(255, 255, 255)","position":"relative","margin-left":"auto","margin-right":"auto"},"mobile":{}},"data":{"component":null},"children":["silex-id-1617899269927-8"],"pageNames":[],"classList":["silex-element-content","website-width","prevent-draggable"],"link":null,"enableEdit":false,"enableDrag":false,"enableDrop":true,"enableResize":{"top":true,"bottom":true,"left":true,"right":true},"selected":false,"useMinHeight":true,"innerHtml":""},{"id":"silex-id-1617900473664-2","tagName":"DIV","type":"html-element","alt":null,"title":null,"isSectionContent":false,"visibility":{"desktop":true,"mobile":true},"style":{"mobile":{},"desktop":{"width":"511px","height":"507px","background-color":"rgb(255, 255, 255)","position":"static"}},"data":{"component":null},"children":[],"pageNames":[],"classList":[],"link":null,"enableEdit":true,"enableDrag":true,"enableDrop":false,"enableResize":{"top":true,"bottom":true,"left":true,"right":true},"selected":false,"useMinHeight":true,"innerHtml":"<iframe width =\"1011\" height=\"479\" src=\"https://editor.p5js.org/Zayatsoff/embed/eV9kLU_vD\"></iframe>"},{"id":"silex-id-1618027742671-0","tagName":"SECTION","type":"section-element","alt":null,"title":null,"isSectionContent":false,"visibility":{"desktop":true,"mobile":true},"style":{"mobile":{},"desktop":{"position":"static"}},"data":{"component":null},"children":["silex-id-1618027742672-1"],"pageNames":["page-home"],"classList":[],"link":null,"enableEdit":false,"enableDrag":true,"enableDrop":true,"enableResize":{"top":false,"bottom":false,"left":false,"right":false},"selected":false,"useMinHeight":true,"innerHtml":""},{"id":"silex-id-1618027742672-1","tagName":"DIV","type":"container-element","alt":null,"title":null,"isSectionContent":true,"visibility":{"desktop":true,"mobile":true},"style":{"desktop":{"height":"169px","background-color":"rgb(255, 255, 255)","position":"relative","margin-left":"auto","margin-right":"auto"},"mobile":{}},"data":{"component":null},"children":["silex-id-1618027764690-5"],"pageNames":[],"classList":["silex-element-content","website-width","prevent-draggable"],"link":null,"enableEdit":false,"enableDrag":false,"enableDrop":true,"enableResize":{"top":true,"bottom":true,"left":true,"right":true},"selected":false,"useMinHeight":true,"innerHtml":""},{"id":"silex-id-1618027759003-3","tagName":"SECTION","type":"section-element","alt":null,"title":null,"isSectionContent":false,"visibility":{"desktop":true,"mobile":true},"style":{"mobile":{},"desktop":{"position":"static"}},"data":{"component":null},"children":["silex-id-1618027759004-4"],"pageNames":["page-home"],"classList":[],"link":null,"enableEdit":false,"enableDrag":true,"enableDrop":true,"enableResize":{"top":false,"bottom":false,"left":false,"right":false},"selected":false,"useMinHeight":true,"innerHtml":""},{"id":"silex-id-1618027759004-4","tagName":"DIV","type":"container-element","alt":null,"title":null,"isSectionContent":true,"visibility":{"desktop":true,"mobile":true},"style":{"desktop":{"height":"100px","background-color":"rgb(255, 255, 255)","position":"relative","margin-left":"auto","margin-right":"auto"},"mobile":{}},"data":{"component":null},"children":["silex-id-1618027824474-7","silex-id-1618028310644-0","silex-id-1618028377300-0","silex-id-1618028548253-1"],"pageNames":[],"classList":["silex-element-content","website-width","prevent-draggable"],"link":null,"enableEdit":false,"enableDrag":false,"enableDrop":true,"enableResize":{"top":true,"bottom":true,"left":true,"right":true},"selected":false,"useMinHeight":true,"innerHtml":""},{"id":"silex-id-1618027764690-5","tagName":"H1","type":"text-element","alt":null,"title":null,"isSectionContent":false,"visibility":{"desktop":true,"mobile":true},"style":{"mobile":{},"desktop":{"width":"685px","height":"60px","position":"absolute","top":"29.5px","left":"158px"}},"data":{"component":null},"children":[],"pageNames":[],"classList":[],"link":null,"enableEdit":true,"enableDrag":true,"enableDrop":false,"enableResize":{"top":true,"bottom":true,"left":true,"right":true},"selected":false,"useMinHeight":true,"innerHtml":"<b>Other Coding Challenges:</b><br>"},{"id":"silex-id-1618027824474-7","tagName":"DIV","type":"html-element","alt":null,"title":null,"isSectionContent":false,"visibility":{"desktop":true,"mobile":true},"style":{"mobile":{},"desktop":{"width":"505px","height":"507px","background-color":"rgb(255, 255, 255)","position":"static"}},"data":{"component":null},"children":[],"pageNames":[],"classList":[],"link":null,"enableEdit":true,"enableDrag":true,"enableDrop":false,"enableResize":{"top":true,"bottom":true,"left":true,"right":true},"selected":false,"useMinHeight":true,"innerHtml":"<iframe width =\"500\" height=\"500\" src=\"https://editor.p5js.org/Zayatsoff/embed/-DuxPrSNT\"></iframe>"},{"id":"silex-id-1618028310644-0","tagName":"DIV","type":"html-element","alt":null,"title":null,"isSectionContent":false,"visibility":{"desktop":true,"mobile":true},"style":{"mobile":{},"desktop":{"width":"505px","height":"507px","background-color":"rgb(255, 255, 255)","position":"static"}},"data":{"component":null},"children":[],"pageNames":[],"classList":[],"link":null,"enableEdit":true,"enableDrag":true,"enableDrop":false,"enableResize":{"top":true,"bottom":true,"left":true,"right":true},"selected":false,"useMinHeight":true,"innerHtml":"<iframe width =\"500\" height=\"500\" src=\"https://editor.p5js.org/Zayatsoff/embed/gR3mb2WZg\"></iframe>"},{"id":"silex-id-1618028377300-0","tagName":"DIV","type":"text-element","alt":null,"title":null,"isSectionContent":false,"visibility":{"desktop":true,"mobile":true},"style":{"mobile":{},"desktop":{"width":"501px","height":"195px","position":"absolute","top":"143px","left":"504px"}},"data":{"component":null},"children":[],"pageNames":[],"classList":[],"link":null,"enableEdit":true,"enableDrag":true,"enableDrop":false,"enableResize":{"top":true,"bottom":true,"left":true,"right":true},"selected":false,"useMinHeight":true,"innerHtml":"<p><b>Snake</b><br></p><p>   Added:</p><p>   •&nbsp; Change of colour;   </p><p>&nbsp;&nbsp;&nbsp;&nbsp;&nbsp;&nbsp;&nbsp;&nbsp;&nbsp;&nbsp;&nbsp;&nbsp;&nbsp; •&nbsp; Snake doesn't die when it hits the wall, instead it teleports.<br></p>"},{"id":"silex-id-1618028548253-1","tagName":"DIV","type":"text-element","alt":null,"title":null,"isSectionContent":false,"visibility":{"desktop":true,"mobile":true},"style":{"mobile":{},"desktop":{"width":"501px","height":"200px","position":"absolute","top":"653px","left":"504px"}},"data":{"component":null},"children":[],"pageNames":[],"classList":[],"link":null,"enableEdit":true,"enableDrag":true,"enableDrop":false,"enableResize":{"top":true,"bottom":true,"left":true,"right":true},"selected":false,"useMinHeight":true,"innerHtml":"<p><b>Game of Life</b><br></p><p>   Added:</p><p>   •&nbsp; Animation slowed down;   </p><p>&nbsp;&nbsp;&nbsp;&nbsp;&nbsp;&nbsp;&nbsp;&nbsp;&nbsp;&nbsp;&nbsp;&nbsp;&nbsp; •&nbsp; Bigger grid.<br></p>"}]}